filespherapy/__init__.py
filespherapy/tools.py
filespherapy-1.0.2.dist-info/top_level.txt
filespherapy-1.0.2.dist-info/METADATA
filespherapy-1.0.2.dist-info/DESCRIPTION.rst
filespherapy-1.0.2.dist-info/metadata.json
filespherapy-1.0.2.dist-info/WHEEL
filespherapy-1.0.2.dist-info/RECORD
