Metadata-Version: 2.0
Name: filespherapy
Version: 1.0.2
Summary: A python library for file path construction and manipulation.
Home-page: https://github.com/phenicle/filespherapy
Author: Phenicle
Author-email: pheniclebeefheart@gmail.com
License: Mozilla Public License 2.0 (MPL 2.0)
Platform: UNKNOWN
